cli_messenger_client/__init__.py
wesphyr-1.0.5.dist-info/METADATA
wesphyr-1.0.5.dist-info/WHEEL
wesphyr-1.0.5.dist-info/entry_points.txt
wesphyr-1.0.5.dist-info/top_level.txt
wesphyr-1.0.5.dist-info/RECORD
