Metadata-Version: 2.4
Name: wesphyr
Version: 1.0.5
Summary: Wesphyr - Global CLI Chat App
License: MIT
Project-URL: Homepage, https://www.fly.dev
Project-URL: Repository, https://github.com/yourusername/wesphyr
Project-URL: Issues, https://github.com/yourusername/wesphyr/issues
Classifier: Development Status :: 5 - Production/Stable
Classifier: Intended Audience :: End Users/Desktop
Classifier: Topic :: Communications :: Chat
Classifier: License :: OSI Approved :: MIT License
Classifier: Programming Language :: Python :: 3
Classifier: Programming Language :: Python :: 3.8
Classifier: Programming Language :: Python :: 3.9
Classifier: Programming Language :: Python :: 3.10
Classifier: Programming Language :: Python :: 3.11
Classifier: Programming Language :: Python :: 3.12
Classifier: Operating System :: OS Independent
Classifier: Environment :: Console
Requires-Python: >=3.8
Requires-Dist: requests>=2.25.0
Requires-Dist: rich>=13.0.0
